LICENSE.md
MANIFEST.in
README.md
setup.cfg
setup.py
django_inlinecss/__init__.py
django_inlinecss/__version__.py
django_inlinecss/conf.py
django_inlinecss/css_loaders.py
django_inlinecss/engines.py
django_inlinecss/models.py
django_inlinecss/templatetags/__init__.py
django_inlinecss/templatetags/inlinecss.py
django_inlinecss/tests/__init__.py
django_inlinecss/tests/test_css_loaders.py
django_inlinecss/tests/test_templatetags.py
q5_django_inlinecss.egg-info/PKG-INFO
q5_django_inlinecss.egg-info/SOURCES.txt
q5_django_inlinecss.egg-info/dependency_links.txt
q5_django_inlinecss.egg-info/not-zip-safe
q5_django_inlinecss.egg-info/requires.txt
q5_django_inlinecss.egg-info/top_level.txt