Metadata-Version: 2.1
Name: q5-django-inlinecss
Version: 0.0.2
Summary: A Django app useful for inlining CSS (primarily for e-mails)
Home-page: https://github.com/roverdotcom/django-inlinecss
Author: Philip Kimmey
Author-email: philip@rover.com
License: MIT
Keywords: html,css,inline,style,email
Platform: UNKNOWN
Classifier: Environment :: Other Environment
Classifier: Environment :: Web Environment
Classifier: Intended Audience :: Developers
Classifier: License :: OSI Approved :: MIT License
Classifier: Operating System :: OS Independent
Classifier: Programming Language :: Python
Classifier: Programming Language :: Python :: 2
Classifier: Programming Language :: Python :: 2.7
Classifier: Programming Language :: Python :: 3
Classifier: Programming Language :: Python :: 3.4
Classifier: Programming Language :: Python :: 3.5
Classifier: Programming Language :: Python :: 3.6
Classifier: Programming Language :: Python :: 3.7
Classifier: Programming Language :: Python :: 3.8
Classifier: Programming Language :: Python :: 3.9
Classifier: Programming Language :: Python :: 3.10
Classifier: Topic :: Communications :: Email
Classifier: Topic :: Text Processing :: Markup :: HTML
Provides-Extra: flake8
Provides-Extra: tests
